{
  "step": [{
      "distance": 0.656,
      "streets": [
        "Boulevard Victor Hugo"
      ],
      "narrative": "Start out going southwest on Boulevard Victor Hugo.",
      "startPoint": {
        "lng": 7.268522,
        "lat": 43.700794
      }
    },
    {
      "distance": 0.254,
      "streets": [
        "Boulevard Gambetta"
      ],
      "narrative": "Turn left onto Boulevard Gambetta.",
      "startPoint": {
        "lng": 7.256238,
        "lat": 43.697533
      }
    },
    {
      "distance": 3.313,
      "streets": [
        "M6098",
        "Promenade des Anglais"
      ],
      "narrative": "Turn right onto M6098/Promenade des Anglais.",
      "startPoint": {
        "lng": 7.25631,
        "lat": 43.693863
      }

    },
    {
      "distance": 0.266,
      "streets": [
        "M6202",
        "Boulevard du Mercantour"
      ],
      "narrative": "Merge onto M6202/Boulevard du Mercantour.",
      "startPoint": {
        "lng": 7.206976,
        "lat": 43.665897
      }

    },
    {
      "distance": 0.521,
      "streets": [],
      "narrative": "Enter next roundabout and take the 2nd exit.",
      "startPoint": {
        "lng": 7.204101,
        "lat": 43.668667
      }

    },
    {
      "distance": 7.824,
      "streets": [
        "A8",
        "La Provençale",
        "E80"
      ],
      "narrative": "Take A8/La Provençale/E80 (Portions toll).",
      "startPoint": {
        "lng": 7.199794,
        "lat": 43.668991
      }

    },
    {
      "distance": 0.201,
      "streets": [],
      "narrative": "Take EXIT 44.",
      "startPoint": {
        "lng": 7.0892,
        "lat": 43.604862
      }
    },
    {
      "distance": 0.295,
      "streets": [],
      "narrative": "Keep left at the fork in the ramp.",
      "startPoint": {
        "lng": 7.085426,
        "lat": 43.603901
      }

    },
    {
      "distance": 0.123,
      "streets": [
        "Route des Trois Moulins"
      ],
      "narrative": "Merge onto Route des Trois Moulins.",
      "startPoint": {
        "lng": 7.083282,
        "lat": 43.603542
      }

    },
    {
      "distance": 0.506,
      "streets": [
        "D35",
        "Route de Grasse"
      ],
      "narrative": "Enter next roundabout and take the 2nd exit onto D35/Route de Grasse. Pass through 1 roundabout.",
      "startPoint": {
        "lng": 7.083783,
        "lat": 43.60181
      }

    },
    {
      "distance": 0.753,
      "streets": [
        "D35BIS"
      ],
      "narrative": "Enter next roundabout and take the 2nd exit onto D35BIS.",
      "startPoint": {
        "lng": 7.08991,
        "lat": 43.596344
      }

    },
    {
      "distance": 1.008,
      "streets": [
        "Route de Saint-Jean"
      ],
      "narrative": "Enter next roundabout and take the 3rd exit onto Route de Saint-Jean.",
      "startPoint": {
        "lng": 7.091075,
        "lat": 43.58604
      }

    },
    {
      "distance": 0.04,
      "streets": [
        "Avenue du Châtaignier"
      ],
      "narrative": "Stay straight to go onto Avenue du Châtaignier.",
      "startPoint": {
        "lng": 7.109178,
        "lat": 43.583004
      }

    },
    {
      "distance": 0.016,
      "streets": [
        "Chemin de la Vigie"
      ],
      "narrative": "Turn sharp right onto Chemin de la Vigie.",
      "startPoint": {
        "lng": 7.109798,
        "lat": 43.58263
      }

    },
    {
      "distance": 0.01,
      "streets": [
        "Chemin de la Vigie"
      ],
      "narrative": "Turn right to stay on Chemin de la Vigie.",
      "startPoint": {
        "lng": 7.109488,
        "lat": 43.582634
      }

    },
    {
      "distance": 0.026,
      "streets": [
        "Avenue du Châtaignier"
      ],
      "narrative": "Turn left onto Avenue du Châtaignier.",
      "startPoint": {
        "lng": 7.109573,
        "lat": 43.582767
      }

    },
    {
      "distance": 0.02,
      "streets": [
        "Route de Saint-Jean"
      ],
      "narrative": "Avenue du Châtaignier becomes Route de Saint-Jean.",
      "startPoint": {
        "lng": 7.109178,
        "lat": 43.583004
      }

    },
    {
      "distance": 0,
      "streets": [],
      "narrative": "Welcome to ANTIBES, PROVENCE-ALPES-CôTE D'AZUR.",
      "startPoint": {
        "lng": 7.108909,
        "lat": 43.583214
      }
    }
  ]
}
